{
  "type": "simpleores:atomic_crafting_table",
  "category": "equipment",
  "ingredient": {
    "S": {
      "item": "minecraft:stick"
    },
    "C": {
      "item": "simpleores:celestine_block"
    },
    "O": {
      "item": "simpleores:obscuridium_block"
    },
    "A": {
      "item": "simpleores:astralite_block"
    },
    "N": {
      "item": "simpleores:nexalite_block"
    },
    "D": {
      "item": "minecraft:diamond_block"
    },
    "Z": {
      "item": "simpleores:zenithra_block"
    }
  },
  "pattern": [
    "  NAAZCDO",
    " NNAAZCDO",
    " N      S",
    "        S",
    "        S",
    "        S",
    "        S",
    "        S",
    "        S"
  ],
  "result": {
    "count": 1,
    "id": "megabreakertools:legendary_hoe"
  }
}