{
  "type": "simpleores:atomic_crafting_table",
  "category": "equipment",
  "ingredient": {
    "S": {
      "item": "minecraft:stick"
    },
    "I": {
      "item": "simpleores:ignithra_block"
    },
    "A": {
      "item": "simpleores:astralite_block"
    },
    "N": {
      "item": "simpleores:nexalite_block"
    },
    "U": {
      "item": "megabreakertools:ultra_shovel"
    },
    "i": {
      "item": "minecraft:iron_block"
    },
    "D": {
      "item": "minecraft:diamond_block"
    }
  },
  "pattern": [
    "      IiD",
    "     NNDi",
    "    NNUAI",
    "     SAA ",
    "    S A  ",
    "   S     ",
    "  S      ",
    " S       ",
    "S        "
  ],
  "result": {
    "count": 1,
    "id": "megabreakertools:mega_ultra_excavator"
  }
}